KSextract/__init__.py
KSextract/extractor.py
ksextract-0.1.0.dist-info/licenses/LICENSE
ksextract-0.1.0.dist-info/METADATA
ksextract-0.1.0.dist-info/WHEEL
ksextract-0.1.0.dist-info/top_level.txt
ksextract-0.1.0.dist-info/RECORD
